setup.py
kyroller/__init__.py
kyroller/cons.py
kyroller/engine.py
kyroller/strategy.py
kyroller/utils.py
kyroller.egg-info/PKG-INFO
kyroller.egg-info/SOURCES.txt
kyroller.egg-info/dependency_links.txt
kyroller.egg-info/entry_points.txt
kyroller.egg-info/requires.txt
kyroller.egg-info/top_level.txt
kyroller/apis/__init__.py
kyroller/apis/trade_api.py
kyroller/bin/__init__.py
kyroller/bin/rollback.py
kyroller/extends/TdxAccount.py
kyroller/extends/__init__.py
kyroller/extends/tdx.py
kyroller/monitors/__init__.py
kyroller/monitors/plot_monitor.py
kyroller/recivers/__init__.py
kyroller/recivers/async_rollback_reciver.py
kyroller/recivers/file.py
kyroller/recivers/rollback_reciver.py
kyroller/recivers/socket_io.py
kyroller/types/__init__.py
kyroller/types/account.py
kyroller/types/account_indicator.py
kyroller/types/back_test_account.py
kyroller/types/bar.py
kyroller/types/deal.py
kyroller/types/exe_rpt.py
kyroller/types/order.py
kyroller/types/position.py
kyroller/types/sub_position.py
kyroller/types/tick.py
kyroller/types/types.py