Metadata-Version: 1.1
Name: kyroller
Version: 0.10.23
Summary: 快雨量化框架
Home-page: http://packages.python.org/kyroller
Author: ShangHai Shilai
Author-email: developers@kuaiyutech.com
License: LGPL
Keywords: stock kuaiyutech
Platform: UNKNOWN
Classifier: Development Status :: 3 - Alpha
Classifier: Environment :: Web Environment
Classifier: Intended Audience :: Developers
Classifier: Operating System :: OS Independent
Classifier: Programming Language :: Python
